parlai/__init__.py
parlai/agents/__init__.py
parlai/agents/coopgame_agent/__init__.py
parlai/agents/coopgame_agent/coopgame_agent.py
parlai/agents/coopgame_agent/modules.py
parlai/agents/drqa/__init__.py
parlai/agents/drqa/config.py
parlai/agents/drqa/drqa.py
parlai/agents/drqa/layers.py
parlai/agents/drqa/model.py
parlai/agents/drqa/rnn_reader.py
parlai/agents/drqa/utils.py
parlai/agents/example_seq2seq/__init__.py
parlai/agents/example_seq2seq/example_seq2seq.py
parlai/agents/fairseq/__init__.py
parlai/agents/fairseq/fairseq.py
parlai/agents/ibm_seq2seq/__init__.py
parlai/agents/ibm_seq2seq/ibm_seq2seq.py
parlai/agents/ir_baseline/__init__.py
parlai/agents/ir_baseline/ir_baseline.py
parlai/agents/language_model/__init__.py
parlai/agents/language_model/language_model.py
parlai/agents/language_model/modules.py
parlai/agents/legacy_agents/__init__.py
parlai/agents/legacy_agents/memnn/__init__.py
parlai/agents/legacy_agents/memnn/memnn_v0.py
parlai/agents/legacy_agents/memnn/modules_v0.py
parlai/agents/legacy_agents/memnn_luatorch_cpu/__init__.py
parlai/agents/legacy_agents/memnn_luatorch_cpu/examples/__init__.py
parlai/agents/legacy_agents/memnn_luatorch_cpu/examples/full_task_train.py
parlai/agents/legacy_agents/seq2seq/__init__.py
parlai/agents/legacy_agents/seq2seq/dict_v0.py
parlai/agents/legacy_agents/seq2seq/dict_v1.py
parlai/agents/legacy_agents/seq2seq/modules_v0.py
parlai/agents/legacy_agents/seq2seq/modules_v1.py
parlai/agents/legacy_agents/seq2seq/seq2seq_v0.py
parlai/agents/legacy_agents/seq2seq/seq2seq_v1.py
parlai/agents/legacy_agents/seq2seq/torch_agent_v1.py
parlai/agents/legacy_agents/seq2seq/utils_v0.py
parlai/agents/legacy_agents/seq2seq/utils_v1.py
parlai/agents/local_human/__init__.py
parlai/agents/local_human/local_human.py
parlai/agents/memnn/__init__.py
parlai/agents/memnn/memnn.py
parlai/agents/memnn/modules.py
parlai/agents/mlb_vqa/__init__.py
parlai/agents/mlb_vqa/dropout.py
parlai/agents/mlb_vqa/gru.py
parlai/agents/mlb_vqa/loadstates.py
roboy_parlai-0.1.post3.dist-info/LICENSE
roboy_parlai-0.1.post3.dist-info/METADATA
roboy_parlai-0.1.post3.dist-info/WHEEL
roboy_parlai-0.1.post3.dist-info/top_level.txt
roboy_parlai-0.1.post3.dist-info/RECORD
