Metadata-Version: 2.1
Name: roboy-parlai
Version: 0.1.post3
Summary: Unified API for accessing dialog datasets.
Home-page: http://parl.ai/
Author: UNKNOWN
Author-email: UNKNOWN
License: BSD License
Requires-Dist: requests
Requires-Dist: numpy
Requires-Dist: Pillow
Requires-Dist: pyzmq
Requires-Dist: h5py
Requires-Dist: gitpython
Requires-Dist: torchtext
Requires-Dist: stop-words
